[ {
  "firstName" : "ema",
  "lastName" : "pirvanus",
  "contact" : {
    "phoneNumber" : "4444444444",
    "emailAddress" : "ema@gmail.com",
    "address" : {
      "street" : "dsff",
      "streetNumber" : "12"
    }
  },
  "education" : [ {
    "collegeName" : "cdov",
    "startDate" : "2012",
    "endDate" : "present",
    "degree" : "dkfd"
  } ],
  "workExperience" : [ {
    "companyName" : "fnb",
    "jobTitle" : "df",
    "startDate" : "2013",
    "endDate" : "present",
    "jobDescription" : "fn"
  } ],
  "skills" : [ ],
  "githubLink" : "https://"
}, {
  "firstName" : "fhdgfd",
  "lastName" : "dfgbfb",
  "contact" : {
    "phoneNumber" : "3333333333",
    "emailAddress" : "ema@gmail.com",
    "address" : {
      "street" : "efrgb",
      "streetNumber" : "12"
    }
  },
  "education" : [ ],
  "workExperience" : [ ],
  "skills" : [ ],
  "githubLink" : "https://"
}, {
  "firstName" : "dfvfg",
  "lastName" : "dfbfgb",
  "contact" : {
    "phoneNumber" : "2222222222",
    "emailAddress" : "ema@gmail.com",
    "address" : {
      "street" : "12121",
      "streetNumber" : "122"
    }
  },
  "education" : [ ],
  "workExperience" : [ ],
  "skills" : [ ],
  "githubLink" : "https://"
}, {
  "firstName" : "dgvfdb",
  "lastName" : "dfbfdgb",
  "contact" : {
    "phoneNumber" : "4444444444",
    "emailAddress" : "ema@gmail.com",
    "address" : {
      "street" : "vdfbfd",
      "streetNumber" : "12"
    }
  },
  "education" : [ ],
  "workExperience" : [ {
    "companyName" : "gbfcbdf",
    "jobTitle" : "dfbg",
    "startDate" : "2222",
    "endDate" : "2222",
    "jobDescription" : "fdgbn"
  } ],
  "skills" : [ "dfgbg" ],
  "githubLink" : "https://"
}, {
  "firstName" : "dcvs",
  "lastName" : "sdc",
  "contact" : {
    "phoneNumber" : "2222222222",
    "emailAddress" : "ema@girl.com",
    "address" : {
      "street" : "sdcv",
      "streetNumber" : "12"
    }
  },
  "education" : [ ],
  "workExperience" : [ ],
  "skills" : [ ],
  "githubLink" : "http://"
}, {
  "firstName" : "fjgn",
  "lastName" : "rgff",
  "contact" : {
    "phoneNumber" : "2222222222",
    "emailAddress" : "ema@gmail.com",
    "address" : {
      "street" : "gb",
      "streetNumber" : "21"
    }
  },
  "education" : [ {
    "collegeName" : "dsfg",
    "startDate" : "2222",
    "endDate" : "2222",
    "degree" : "gdd"
  } ],
  "workExperience" : [ {
    "companyName" : "dfgfb",
    "jobTitle" : "dsgfb",
    "startDate" : "2111",
    "endDate" : "1111",
    "jobDescription" : "fbgnhbgfg"
  }, {
    "companyName" : "dssdg",
    "jobTitle" : "b",
    "startDate" : "1111",
    "endDate" : "1111",
    "jobDescription" : "fbbd"
  } ],
  "skills" : [ "frgb" ],
  "githubLink" : "https://"
}, {
  "firstName" : "dsfbg",
  "lastName" : "dfb",
  "contact" : {
    "phoneNumber" : "1111111111",
    "emailAddress" : "ema@gmail.com",
    "address" : {
      "street" : "fsdfdb",
      "streetNumber" : "12"
    }
  },
  "education" : [ ],
  "workExperience" : [ {
    "companyName" : "cdv",
    "jobTitle" : "sdvf",
    "startDate" : "1111",
    "endDate" : "1111",
    "jobDescription" : "edw"
  } ],
  "skills" : [ ],
  "githubLink" : "https://"
}, {
  "firstName" : "fdbg",
  "lastName" : "dfg",
  "contact" : {
    "phoneNumber" : "1111111111",
    "emailAddress" : "ema@gmail.com",
    "address" : {
      "street" : "df",
      "streetNumber" : "12"
    }
  },
  "education" : [ {
    "collegeName" : "edjnvb",
    "startDate" : "1234",
    "endDate" : "2222",
    "degree" : "bachelor"
  } ],
  "workExperience" : [ ],
  "skills" : [ ],
  "githubLink" : "https://"
} ]